exonware/__init__.py
exonware/xwlazy/__init__.py
exonware/xwlazy/config.py
exonware/xwlazy/contracts.py
exonware/xwlazy/defs.py
exonware/xwlazy/errors.py
exonware/xwlazy/facade.py
exonware/xwlazy/version.py
exonware/xwlazy/common/__init__.py
exonware/xwlazy/common/base.py
exonware/xwlazy/common/cache.py
exonware/xwlazy/common/logger.py
exonware/xwlazy/common/utils.py
exonware/xwlazy/common/services/__init__.py
exonware/xwlazy/common/services/dependency_mapper.py
exonware/xwlazy/common/services/install_async_utils.py
exonware/xwlazy/common/services/install_cache_utils.py
exonware/xwlazy/common/services/keyword_detection.py
exonware/xwlazy/common/services/spec_cache.py
exonware/xwlazy/common/services/state_manager.py
exonware/xwlazy/common/strategies/__init__.py
exonware/xwlazy/common/strategies/caching_dict.py
exonware/xwlazy/common/strategies/caching_installation.py
exonware/xwlazy/common/strategies/caching_lfu.py
exonware/xwlazy/common/strategies/caching_lru.py
exonware/xwlazy/common/strategies/caching_multitier.py
exonware/xwlazy/common/strategies/caching_ttl.py
exonware/xwlazy/host/__init__.py
exonware/xwlazy/host/conf.py
exonware/xwlazy/module/__init__.py
exonware/xwlazy/module/base.py
exonware/xwlazy/module/data.py
exonware/xwlazy/module/facade.py
exonware/xwlazy/module/importer_engine.py
exonware/xwlazy/module/partial_module_detector.py
exonware/xwlazy/module/strategies/__init__.py
exonware/xwlazy/module/strategies/module_helper_lazy.py
exonware/xwlazy/module/strategies/module_helper_simple.py
exonware/xwlazy/module/strategies/module_manager_advanced.py
exonware/xwlazy/module/strategies/module_manager_simple.py
exonware/xwlazy/package/__init__.py
exonware/xwlazy/package/base.py
exonware/xwlazy/package/conf.py
exonware/xwlazy/package/data.py
exonware/xwlazy/package/facade.py
exonware/xwlazy/package/services/__init__.py
exonware/xwlazy/package/services/async_install_handle.py
exonware/xwlazy/package/services/config_manager.py
exonware_xwlazy-0.1.0.23.dist-info/METADATA
exonware_xwlazy-0.1.0.23.dist-info/WHEEL
exonware_xwlazy-0.1.0.23.dist-info/licenses/LICENSE
exonware_xwlazy-0.1.0.23.dist-info/RECORD
